README.md
setup.py
bin/pyawabi
pure_pyawabi.egg-info/PKG-INFO
pure_pyawabi.egg-info/SOURCES.txt
pure_pyawabi.egg-info/dependency_links.txt
pure_pyawabi.egg-info/top_level.txt
pyawabi/__init__.py
pyawabi/awabi.py
pyawabi/dic.py
pyawabi/lattice.py
pyawabi/mecabrc.py
pyawabi/tokenizer.py