Metadata-Version: 2.1
Name: pure-pyawabi
Version: 0.2.2
Summary: A morphological analyzer awabi clone
Home-page: https://github.com/nakagami/pure-pyawabi/
Author: Hajime Nakagami
Author-email: nakagami@gmail.com
License: MIT
Keywords: MeCab
Platform: UNKNOWN
Classifier: License :: OSI Approved :: MIT License
Classifier: Development Status :: 4 - Beta
Classifier: Intended Audience :: Developers
Classifier: Programming Language :: Python
Classifier: Programming Language :: Python :: 3.8
Classifier: Operating System :: POSIX
